karrio/mappers/sendcloud/__init__.py
karrio/mappers/sendcloud/mapper.py
karrio/mappers/sendcloud/proxy.py
karrio/mappers/sendcloud/settings.py
karrio/plugins/sendcloud/__init__.py
karrio/providers/sendcloud/__init__.py
karrio/providers/sendcloud/error.py
karrio/providers/sendcloud/rate.py
karrio/providers/sendcloud/tracking.py
karrio/providers/sendcloud/units.py
karrio/providers/sendcloud/utils.py
karrio/providers/sendcloud/pickup/__init__.py
karrio/providers/sendcloud/pickup/cancel.py
karrio/providers/sendcloud/pickup/create.py
karrio/providers/sendcloud/pickup/update.py
karrio/providers/sendcloud/shipment/__init__.py
karrio/providers/sendcloud/shipment/cancel.py
karrio/providers/sendcloud/shipment/create.py
karrio/schemas/sendcloud/__init__.py
karrio/schemas/sendcloud/auth_request.py
karrio/schemas/sendcloud/auth_response.py
karrio/schemas/sendcloud/error.py
karrio/schemas/sendcloud/rate_request.py
karrio/schemas/sendcloud/rate_response.py
karrio/schemas/sendcloud/shipment_request.py
karrio/schemas/sendcloud/shipment_response.py
karrio/schemas/sendcloud/tracking_request.py
karrio/schemas/sendcloud/tracking_response.py
karrio_sendcloud-2025.5rc9.dist-info/METADATA
karrio_sendcloud-2025.5rc9.dist-info/WHEEL
karrio_sendcloud-2025.5rc9.dist-info/entry_points.txt
karrio_sendcloud-2025.5rc9.dist-info/top_level.txt
karrio_sendcloud-2025.5rc9.dist-info/RECORD
